{
  "milestone": "CGHSTC-34-M50",
  "status": "m50_literature_guided_ordering_diagnostic",
  "literature_analogy": "nonequilibrium pattern-formation amplitude equation",
  "outcome_classification": "quality_contamination_dominant",
  "primary_activation_auc_like": 0.32051282051282054,
  "primary_residual_auc_like": 0.4052631578947368,
  "primary_activation_balanced_accuracy": 0.3269230769230769,
  "primary_residual_direction_balanced_accuracy": 0.43157894736842106,
  "heldout_n": 29,
  "trained_on_endpoint_residuals": false,
  "trained_on_A_inferred": false,
  "quality_used_as_physical_feature": false,
  "endpoint_bridge_after_freeze": true,
  "m36_refit": false,
  "mature_velocity_law_changed": false,
  "manuscript_rewritten": false,
  "governor_promoted": false,
  "ugc07125_treated_as_clean_scalar_object": false,
  "ode_parameters": {
    "a": 0.9,
    "b": 0.8,
    "c": 0.4,
    "d": 0.7,
    "steps": 12,
    "dt": 0.35
  }
}
